svd2py/__init__.py
svd2py/app.py
svd2py/objects.py
svd2py/parser.py
svd2py-1.0.2.dist-info/LICENSE
svd2py-1.0.2.dist-info/METADATA
svd2py-1.0.2.dist-info/WHEEL
svd2py-1.0.2.dist-info/entry_points.txt
svd2py-1.0.2.dist-info/RECORD
