Metadata-Version: 2.1
Name: svd2py
Version: 1.0.2
Summary: CMSIS SVD file parser that allows to convert SVD format to Python data structure
Home-page: https://github.com/gembcior/svd2py
License: MIT
Author: Gembcior
Author-email: gembcior@gmail.com
Requires-Python: >=3.9,<4.0
Classifier: Environment :: Console
Classifier: License :: OSI Approved :: MIT License
Classifier: Operating System :: POSIX :: Linux
Classifier: Programming Language :: Python :: 3
Classifier: Programming Language :: Python :: 3.9
Classifier: Programming Language :: Python :: 3.10
Classifier: Programming Language :: Python :: 3.11
Classifier: Programming Language :: Python :: 3.12
Requires-Dist: click (>=8.1,<9.0)
Requires-Dist: pyyaml (>=6.0,<7.0)
